odoo/addons/mail_track_diff_only/README.rst
odoo/addons/mail_track_diff_only/__init__.py
odoo/addons/mail_track_diff_only/__manifest__.py
odoo/addons/mail_track_diff_only/i18n/mail_track_diff_only.pot
odoo/addons/mail_track_diff_only/models/__init__.py
odoo/addons/mail_track_diff_only/models/mail_thread.py
odoo/addons/mail_track_diff_only/readme/CONTRIBUTORS.rst
odoo/addons/mail_track_diff_only/readme/DESCRIPTION.rst
odoo/addons/mail_track_diff_only/readme/INSTALL.rst
odoo/addons/mail_track_diff_only/readme/USAGE.rst
odoo/addons/mail_track_diff_only/static/description/icon.png
odoo/addons/mail_track_diff_only/static/description/index.html
odoo/addons/mail_track_diff_only/tests/__init__.py
odoo/addons/mail_track_diff_only/tests/test_mail_tracking.py
odoo11_addon_mail_track_diff_only-11.0.1.0.0.99.dev6.dist-info/METADATA
odoo11_addon_mail_track_diff_only-11.0.1.0.0.99.dev6.dist-info/WHEEL
odoo11_addon_mail_track_diff_only-11.0.1.0.0.99.dev6.dist-info/top_level.txt
odoo11_addon_mail_track_diff_only-11.0.1.0.0.99.dev6.dist-info/RECORD
